ECOv002_calval_tables/ECOv002_calval_tables.py
ECOv002_calval_tables/__init__.py
ECOv002_calval_tables/combined_eco_flux_EC_filtered.csv
ECOv002_calval_tables/ec_lib.py
ECOv002_calval_tables/error_funcs.py
ECOv002_calval_tables/load_tables.py
ECOv002_calval_tables/metadata_ebc_filt.csv
ECOv002_calval_tables/plot_funcs.py
ECOv002_calval_tables/plot_single_model.py
ECOv002_calval_tables/upscale_to_daylight.py
ECOv002_calval_tables/version.py
ecov002_calval_tables-1.7.1.dist-info/licenses/LICENSE
tests/test_import_ECOv002_calval_tables.py
tests/test_import_dependencies.py
tests/test_load_calval_table.py
tests/test_load_metadata_ebc_filt.py
ecov002_calval_tables-1.7.1.dist-info/METADATA
ecov002_calval_tables-1.7.1.dist-info/WHEEL
ecov002_calval_tables-1.7.1.dist-info/top_level.txt
ecov002_calval_tables-1.7.1.dist-info/RECORD
