Metadata-Version: 2.4
Name: ECOv002-calval-tables
Version: 1.7.1
Summary: Priestley-Taylor Jet Propulsion Laboratory Soil Moisutre Evapotranspiration Model
Author-email: Gregory Halverson <gregory.h.halverson@jpl.nasa.gov>, Zoe Pierrat <zoe.a.pierrat@jpl.nasa.gov>
Project-URL: Homepage, https://github.com/gregory-halverson/ECOv002-calval-tables
Classifier: Programming Language :: Python :: 3
Classifier: Operating System :: OS Independent
Requires-Python: >=3.10
License-File: LICENSE
Requires-Dist: daylight-evapotranspiration>=v1.3.4
Requires-Dist: pandas
Requires-Dist: geopandas
Requires-Dist: numpy
Requires-Dist: tables
Requires-Dist: scikit-learn
Requires-Dist: scipy
Requires-Dist: matplotlib
Requires-Dist: shapely
Provides-Extra: dev
Requires-Dist: build; extra == "dev"
Requires-Dist: pytest>=6.0; extra == "dev"
Requires-Dist: pytest-cov; extra == "dev"
Requires-Dist: jupyter; extra == "dev"
Requires-Dist: pytest; extra == "dev"
Requires-Dist: twine; extra == "dev"
Dynamic: license-file
